{
  "$schema": "https://ui.shadcn.com/schema/registry-item.json",
  "name": "kokonut-file-upload",
  "title": "File Upload",
  "author": "kokonutUI",
  "description": "Validates, uploads, cancels, and reports progress for a dropped or selected file through a caller-supplied async transport.",
  "dependencies": [
    "clsx@2.1.1",
    "lucide-react@0.556.0",
    "motion@12.23.25",
    "tailwind-merge@3.4.0"
  ],
  "registryDependencies": [],
  "files": [
    {
      "path": "registry/sources/kokonut-ui/components/kokonut-file-upload/file-upload.tsx",
      "content": "\"use client\"\n\n/**\n * @author: @dorianbaffier\n * @description: File Upload\n * @version: 1.0.0\n * @date: 2025-06-26\n * @license: MIT\n * @website: https://kokonutui.com\n * @github: https://github.com/kokonut-labs/kokonutui\n */\n\nimport { Check, UploadCloud, X } from \"lucide-react\"\nimport { AnimatePresence, motion, useReducedMotion } from \"motion/react\"\nimport {\n  type DragEvent,\n  useCallback,\n  useEffect,\n  useId,\n  useRef,\n  useState,\n} from \"react\"\n\nimport { cn } from \"../../lib/utils\"\n\ntype FileStatus = \"idle\" | \"dragging\" | \"uploading\" | \"complete\" | \"error\"\n\nexport interface FileUploadError {\n  message: string\n  code: string\n}\n\nexport interface FileUploadContext {\n  signal: AbortSignal\n  onProgress: (progress: number) => void\n}\n\nexport interface FileUploadProps {\n  uploadFile: (file: File, context: FileUploadContext) => Promise<void>\n  onUploadSuccess?: (file: File) => void\n  onUploadError?: (error: FileUploadError) => void\n  onFileRemove?: (file: File) => void\n  acceptedFileTypes?: string[]\n  maxFileSize?: number\n  validateFile?: (file: File) => FileUploadError | null\n  className?: string\n}\n\nconst DEFAULT_MAX_FILE_SIZE = 5 * 1024 * 1024\nconst FILE_SIZES = [\"Bytes\", \"KB\", \"MB\", \"GB\", \"TB\", \"PB\", \"EB\", \"ZB\", \"YB\"] as const\n\nfunction formatBytes(bytes: number, decimals = 2): string {\n  if (!(Number.isFinite(bytes) && bytes > 0)) return \"0 Bytes\"\n  const index = Math.min(\n    Math.floor(Math.log(bytes) / Math.log(1024)),\n    FILE_SIZES.length - 1,\n  )\n  return `${Number.parseFloat((bytes / 1024 ** index).toFixed(Math.max(0, decimals)))} ${FILE_SIZES[index]}`\n}\n\nfunction acceptsFile(file: File, accept: string): boolean {\n  const token = accept.trim().toLowerCase()\n  if (!token) return false\n  if (token.startsWith(\".\")) return file.name.toLowerCase().endsWith(token)\n  if (token.endsWith(\"/*\")) return file.type.toLowerCase().startsWith(token.slice(0, -1))\n  return file.type.toLowerCase() === token\n}\n\nfunction UploadIllustration({ reducedMotion }: { reducedMotion: boolean }) {\n  return (\n    <div className=\"relative h-16 w-16\">\n      <svg aria-hidden=\"true\" className=\"h-full w-full\" fill=\"none\" viewBox=\"0 0 100 100\">\n        <circle\n          className=\"stroke-gray-200 dark:stroke-gray-700\"\n          cx=\"50\"\n          cy=\"50\"\n          r=\"45\"\n          strokeDasharray=\"4 4\"\n          strokeWidth=\"2\"\n        >\n          {!reducedMotion && (\n            <animateTransform\n              attributeName=\"transform\"\n              dur=\"60s\"\n              from=\"0 50 50\"\n              repeatCount=\"indefinite\"\n              to=\"360 50 50\"\n              type=\"rotate\"\n            />\n          )}\n        </circle>\n\n        <path\n          className=\"fill-blue-100 stroke-blue-500 dark:fill-blue-900/30 dark:stroke-blue-400\"\n          d=\"M30 35H70C75 35 75 40 75 40V65C75 70 70 70 70 70H30C25 70 25 65 25 65V40C25 35 30 35 30 35Z\"\n          strokeWidth=\"2\"\n        >\n          {!reducedMotion && (\n            <animate\n              attributeName=\"d\"\n              dur=\"2s\"\n              repeatCount=\"indefinite\"\n              values=\"M30 35H70C75 35 75 40 75 40V65C75 70 70 70 70 70H30C25 70 25 65 25 65V40C25 35 30 35 30 35Z;M30 38H70C75 38 75 43 75 43V68C75 73 70 73 70 73H30C25 73 25 68 25 68V43C25 38 30 38 30 38Z;M30 35H70C75 35 75 40 75 40V65C75 70 70 70 70 70H30C25 70 25 65 25 65V40C25 35 30 35 30 35Z\"\n            />\n          )}\n        </path>\n\n        <path\n          className=\"stroke-blue-500 dark:stroke-blue-400\"\n          d=\"M30 35C30 35 35 35 40 35C45 35 45 30 50 30C55 30 55 35 60 35C65 35 70 35 70 35\"\n          strokeWidth=\"2\"\n        />\n\n        <g className=\"translate-y-2 transform\">\n          <line\n            className=\"stroke-blue-500 dark:stroke-blue-400\"\n            strokeLinecap=\"round\"\n            strokeWidth=\"2\"\n            x1=\"50\"\n            x2=\"50\"\n            y1=\"45\"\n            y2=\"60\"\n          >\n            {!reducedMotion && (\n              <animate attributeName=\"y2\" dur=\"2s\" repeatCount=\"indefinite\" values=\"60;55;60\" />\n            )}\n          </line>\n          <polyline\n            className=\"stroke-blue-500 dark:stroke-blue-400\"\n            fill=\"none\"\n            points=\"42,52 50,45 58,52\"\n            strokeLinecap=\"round\"\n            strokeLinejoin=\"round\"\n            strokeWidth=\"2\"\n          >\n            {!reducedMotion && (\n              <animate\n                attributeName=\"points\"\n                dur=\"2s\"\n                repeatCount=\"indefinite\"\n                values=\"42,52 50,45 58,52;42,47 50,40 58,47;42,52 50,45 58,52\"\n              />\n            )}\n          </polyline>\n        </g>\n      </svg>\n    </div>\n  )\n}\n\nfunction UploadingAnimation({\n  progress,\n  reducedMotion,\n}: {\n  progress: number\n  reducedMotion: boolean\n}) {\n  const maskId = `upload-progress-${useId().replaceAll(\":\", \"\")}`\n  return (\n    <div className=\"relative h-16 w-16\">\n      <svg\n        aria-label={`Upload progress: ${Math.round(progress)}%`}\n        className=\"h-full w-full\"\n        fill=\"none\"\n        role=\"img\"\n        viewBox=\"0 0 240 240\"\n      >\n        <title>Upload progress</title>\n        <defs>\n          <mask id={maskId}>\n            <rect fill=\"black\" height=\"240\" width=\"240\" />\n            <circle\n              cx=\"120\"\n              cy=\"120\"\n              fill=\"white\"\n              r=\"120\"\n              strokeDasharray={`${(progress / 100) * 754}, 754`}\n              transform=\"rotate(-90 120 120)\"\n            />\n          </mask>\n        </defs>\n        <style>{`\n          @keyframes kokonut-upload-cw { from { transform: rotate(0deg); } to { transform: rotate(360deg); } }\n          @keyframes kokonut-upload-ccw { from { transform: rotate(360deg); } to { transform: rotate(0deg); } }\n          .kokonut-upload-rings circle { transform-origin: 120px 120px; }\n          .kokonut-upload-rings circle:nth-child(odd) { animation: kokonut-upload-cw 8s linear infinite; }\n          .kokonut-upload-rings circle:nth-child(even) { animation: kokonut-upload-ccw 8s linear infinite; }\n          .kokonut-upload-rings[data-reduced-motion] circle { animation: none !important; }\n          @media (prefers-reduced-motion: reduce) { .kokonut-upload-rings circle { animation: none; } }\n        `}</style>\n        <g\n          className=\"kokonut-upload-rings\"\n          data-reduced-motion={reducedMotion || undefined}\n          mask={`url(#${maskId})`}\n          strokeDasharray=\"18% 40%\"\n          strokeWidth=\"10\"\n        >\n          <circle cx=\"120\" cy=\"120\" opacity=\"0.95\" r=\"150\" stroke=\"#FF2E7E\" />\n          <circle cx=\"120\" cy=\"120\" opacity=\"0.95\" r=\"140\" stroke=\"#FFD600\" />\n          <circle cx=\"120\" cy=\"120\" opacity=\"0.95\" r=\"130\" stroke=\"#00E5FF\" />\n          <circle cx=\"120\" cy=\"120\" opacity=\"0.95\" r=\"120\" stroke=\"#FF3D71\" />\n          <circle cx=\"120\" cy=\"120\" opacity=\"0.95\" r=\"110\" stroke=\"#4ADE80\" />\n          <circle cx=\"120\" cy=\"120\" opacity=\"0.95\" r=\"100\" stroke=\"#2196F3\" />\n          <circle cx=\"120\" cy=\"120\" opacity=\"0.95\" r=\"90\" stroke=\"#FFA726\" />\n          <circle cx=\"120\" cy=\"120\" opacity=\"0.95\" r=\"80\" stroke=\"#FF1493\" />\n          <circle cx=\"120\" cy=\"120\" opacity=\"0.95\" r=\"70\" stroke=\"#FFEB3B\" />\n          <circle cx=\"120\" cy=\"120\" opacity=\"0.95\" r=\"60\" stroke=\"#00BCD4\" />\n          <circle cx=\"120\" cy=\"120\" opacity=\"0.95\" r=\"50\" stroke=\"#FF4081\" />\n          <circle cx=\"120\" cy=\"120\" opacity=\"0.95\" r=\"40\" stroke=\"#76FF03\" />\n          <circle cx=\"120\" cy=\"120\" opacity=\"0.95\" r=\"30\" stroke=\"#448AFF\" />\n          <circle cx=\"120\" cy=\"120\" opacity=\"0.95\" r=\"20\" stroke=\"#FF3D00\" />\n        </g>\n      </svg>\n    </div>\n  )\n}\n\nfunction normalizeUploadError(error: unknown): FileUploadError {\n  if (\n    error &&\n    typeof error === \"object\" &&\n    \"message\" in error &&\n    typeof error.message === \"string\" &&\n    \"code\" in error &&\n    typeof error.code === \"string\"\n  ) {\n    return { message: error.message, code: error.code }\n  }\n  return {\n    message: error instanceof Error ? error.message : \"Upload failed\",\n    code: \"UPLOAD_FAILED\",\n  }\n}\n\nexport default function FileUpload({\n  uploadFile,\n  onUploadSuccess,\n  onUploadError,\n  onFileRemove,\n  acceptedFileTypes = [],\n  maxFileSize = DEFAULT_MAX_FILE_SIZE,\n  validateFile,\n  className,\n}: FileUploadProps) {\n  const [file, setFile] = useState<File | null>(null)\n  const [status, setStatus] = useState<FileStatus>(\"idle\")\n  const [progress, setProgress] = useState(0)\n  const [error, setError] = useState<FileUploadError | null>(null)\n  const fileInputRef = useRef<HTMLInputElement>(null)\n  const uploadAbortRef = useRef<AbortController | null>(null)\n  const reducedMotion = useReducedMotion() ?? false\n  const safeMaxFileSize =\n    Number.isFinite(maxFileSize) && maxFileSize > 0\n      ? maxFileSize\n      : DEFAULT_MAX_FILE_SIZE\n\n  useEffect(\n    () => () => {\n      uploadAbortRef.current?.abort()\n    },\n    [],\n  )\n\n  const reportError = useCallback(\n    (nextError: FileUploadError) => {\n      setError(nextError)\n      setStatus(\"error\")\n      onUploadError?.(nextError)\n    },\n    [onUploadError],\n  )\n\n  const validate = useCallback(\n    (selectedFile: File): FileUploadError | null => {\n      if (selectedFile.size > safeMaxFileSize) {\n        return {\n          message: `File size exceeds ${formatBytes(safeMaxFileSize)}`,\n          code: \"FILE_TOO_LARGE\",\n        }\n      }\n      if (\n        acceptedFileTypes.length > 0 &&\n        !acceptedFileTypes.some((type) => acceptsFile(selectedFile, type))\n      ) {\n        return {\n          message: `File type must match ${acceptedFileTypes.join(\", \")}`,\n          code: \"INVALID_FILE_TYPE\",\n        }\n      }\n      return validateFile?.(selectedFile) ?? null\n    },\n    [acceptedFileTypes, safeMaxFileSize, validateFile],\n  )\n\n  const handleFileSelect = useCallback(\n    async (selectedFile: File | null) => {\n      if (!selectedFile || status === \"uploading\") return\n      setError(null)\n      const validationError = validate(selectedFile)\n      if (validationError) {\n        reportError(validationError)\n        return\n      }\n\n      const controller = new AbortController()\n      uploadAbortRef.current?.abort()\n      uploadAbortRef.current = controller\n      setFile(selectedFile)\n      setProgress(0)\n      setStatus(\"uploading\")\n\n      try {\n        await uploadFile(selectedFile, {\n          signal: controller.signal,\n          onProgress: (nextProgress) => {\n            if (controller.signal.aborted) return\n            setProgress(Math.min(100, Math.max(0, nextProgress)))\n          },\n        })\n        if (controller.signal.aborted) return\n        setProgress(100)\n        setStatus(\"complete\")\n        onUploadSuccess?.(selectedFile)\n      } catch (uploadError) {\n        if (!controller.signal.aborted) reportError(normalizeUploadError(uploadError))\n      } finally {\n        if (uploadAbortRef.current === controller) uploadAbortRef.current = null\n      }\n    },\n    [onUploadSuccess, reportError, status, uploadFile, validate],\n  )\n\n  const resetState = useCallback(() => {\n    uploadAbortRef.current?.abort()\n    uploadAbortRef.current = null\n    if (file) onFileRemove?.(file)\n    setFile(null)\n    setStatus(\"idle\")\n    setProgress(0)\n    setError(null)\n  }, [file, onFileRemove])\n\n  const handleDragOver = (event: DragEvent<HTMLDivElement>) => {\n    event.preventDefault()\n    if (status !== \"uploading\" && status !== \"complete\") setStatus(\"dragging\")\n  }\n\n  const handleDragLeave = (event: DragEvent<HTMLDivElement>) => {\n    event.preventDefault()\n    if (event.currentTarget.contains(event.relatedTarget as Node | null)) return\n    if (status === \"dragging\") setStatus(\"idle\")\n  }\n\n  const handleDrop = (event: DragEvent<HTMLDivElement>) => {\n    event.preventDefault()\n    if (status === \"uploading\" || status === \"complete\") return\n    setStatus(\"idle\")\n    void handleFileSelect(event.dataTransfer.files?.[0] ?? null)\n  }\n\n  const idle = status === \"idle\" || status === \"dragging\" || status === \"error\"\n\n  return (\n    <div\n      aria-busy={status === \"uploading\"}\n      aria-label=\"File upload\"\n      className={cn(\"relative mx-auto w-full max-w-sm\", className)}\n      role=\"group\"\n    >\n      <div className=\"group relative w-full rounded-xl bg-white p-0.5 ring-1 ring-gray-200 dark:bg-black dark:ring-white/10\">\n        <div className=\"absolute inset-x-0 -top-px h-px bg-gradient-to-r from-transparent via-blue-500/20 to-transparent\" />\n        <div className=\"relative w-full rounded-[10px] bg-gray-50/50 p-1.5 dark:bg-white/[0.02]\">\n          <div\n            className={cn(\n              \"relative overflow-hidden rounded-lg border border-gray-100 bg-white dark:border-white/[0.08] dark:bg-black/50\",\n              error && \"border-red-500/50\",\n            )}\n          >\n            <div\n              aria-hidden=\"true\"\n              className={cn(\n                \"pointer-events-none absolute inset-0 bg-blue-500/5 transition-opacity duration-200 motion-reduce:transition-none\",\n                status === \"dragging\" ? \"opacity-100\" : \"opacity-0\",\n              )}\n            />\n\n            <div className=\"relative h-[240px]\">\n              <AnimatePresence mode=\"wait\">\n                {idle ? (\n                  <motion.div\n                    animate={{\n                      opacity: status === \"dragging\" ? 0.8 : 1,\n                      y: 0,\n                      scale: status === \"dragging\" && !reducedMotion ? 0.98 : 1,\n                    }}\n                    className=\"absolute inset-0 flex flex-col items-center justify-center p-6\"\n                    exit={{ opacity: 0, y: reducedMotion ? 0 : -10 }}\n                    initial={{ opacity: 0, y: reducedMotion ? 0 : 10 }}\n                    key=\"dropzone\"\n                    onDragLeave={handleDragLeave}\n                    onDragOver={handleDragOver}\n                    onDrop={handleDrop}\n                    transition={{ duration: reducedMotion ? 0 : 0.2, ease: \"easeOut\" }}\n                  >\n                    <div className=\"mb-4\">\n                      <UploadIllustration reducedMotion={reducedMotion} />\n                    </div>\n                    <div className=\"mb-4 space-y-1.5 text-center\">\n                      <h3 className=\"font-semibold text-gray-900 text-lg tracking-tight dark:text-white\">\n                        Drop a file or browse\n                      </h3>\n                      <p className=\"text-gray-500 text-xs dark:text-gray-400\">\n                        {acceptedFileTypes.length > 0\n                          ? acceptedFileTypes.join(\", \")\n                          : \"Any file type\"}{\" \"}\n                        up to {formatBytes(safeMaxFileSize)}\n                      </p>\n                    </div>\n                    <button\n                      className=\"group/upload flex min-h-11 w-4/5 items-center justify-center gap-2 rounded-lg bg-gray-100 px-4 py-2.5 font-semibold text-gray-900 text-sm transition-colors duration-150 hover:bg-gray-200 focus-visible:outline-none focus-visible:ring-2 focus-visible:ring-blue-500 dark:bg-white/10 dark:text-white dark:hover:bg-white/20\"\n                      onClick={() => fileInputRef.current?.click()}\n                      type=\"button\"\n                    >\n                      Choose file\n                      <UploadCloud className=\"h-4 w-4 transition-transform duration-150 motion-reduce:transition-none [@media(hover:hover)]:group-hover/upload:-translate-y-0.5\" />\n                    </button>\n                    <input\n                      accept={acceptedFileTypes.join(\",\") || undefined}\n                      aria-label=\"Choose file\"\n                      className=\"sr-only\"\n                      onChange={(event) => {\n                        void handleFileSelect(event.target.files?.[0] ?? null)\n                        event.target.value = \"\"\n                      }}\n                      ref={fileInputRef}\n                      type=\"file\"\n                    />\n                  </motion.div>\n                ) : (\n                  <motion.div\n                    animate={{ opacity: 1, scale: 1 }}\n                    className=\"absolute inset-0 flex flex-col items-center justify-center p-6\"\n                    exit={{ opacity: 0, scale: reducedMotion ? 1 : 0.97 }}\n                    initial={{ opacity: 0, scale: reducedMotion ? 1 : 0.97 }}\n                    key={status}\n                    transition={{ duration: reducedMotion ? 0 : 0.2, ease: \"easeOut\" }}\n                  >\n                    <div className=\"mb-4\">\n                      {status === \"complete\" ? (\n                        <div className=\"flex h-16 w-16 items-center justify-center rounded-full bg-emerald-100 text-emerald-700 dark:bg-emerald-950 dark:text-emerald-300\">\n                          <Check aria-hidden=\"true\" className=\"h-7 w-7\" />\n                        </div>\n                      ) : (\n                        <UploadingAnimation progress={progress} reducedMotion={reducedMotion} />\n                      )}\n                    </div>\n                    <div aria-live=\"polite\" className=\"mb-4 max-w-full space-y-1.5 text-center\">\n                      <h3 className=\"truncate font-semibold text-gray-900 text-sm dark:text-white\">\n                        {file?.name}\n                      </h3>\n                      <div className=\"flex items-center justify-center gap-2 text-xs\">\n                        <span className=\"text-gray-500 dark:text-gray-400\">\n                          {formatBytes(file?.size ?? 0)}\n                        </span>\n                        <span className=\"font-medium text-blue-500\">\n                          {status === \"complete\" ? \"Uploaded\" : `${Math.round(progress)}%`}\n                        </span>\n                      </div>\n                    </div>\n                    <button\n                      className=\"flex min-h-11 w-4/5 items-center justify-center gap-2 rounded-lg bg-gray-100 px-4 py-2.5 font-semibold text-gray-900 text-sm transition-colors duration-150 hover:bg-gray-200 focus-visible:outline-none focus-visible:ring-2 focus-visible:ring-blue-500 dark:bg-white/10 dark:text-white dark:hover:bg-white/20\"\n                      onClick={resetState}\n                      type=\"button\"\n                    >\n                      <X aria-hidden=\"true\" className=\"h-4 w-4\" />\n                      {status === \"complete\" ? \"Remove file\" : \"Cancel upload\"}\n                    </button>\n                  </motion.div>\n                )}\n              </AnimatePresence>\n            </div>\n\n            <AnimatePresence>\n              {error && (\n                <motion.div\n                  animate={{ opacity: 1, y: 0 }}\n                  className=\"absolute right-4 bottom-4 left-4 rounded-lg border border-red-500/20 bg-red-50 px-4 py-2 dark:bg-red-950/80\"\n                  exit={{ opacity: 0, y: reducedMotion ? 0 : -6 }}\n                  initial={{ opacity: 0, y: reducedMotion ? 0 : 6 }}\n                  role=\"alert\"\n                  transition={{ duration: reducedMotion ? 0 : 0.16, ease: \"easeOut\" }}\n                >\n                  <p className=\"text-red-700 text-sm dark:text-red-300\">{error.message}</p>\n                </motion.div>\n              )}\n            </AnimatePresence>\n          </div>\n        </div>\n      </div>\n    </div>\n  )\n}\n",
      "type": "registry:component",
      "target": "@components/taste-blocks/kokonut-file-upload.tsx"
    },
    {
      "path": "registry/sources/kokonut-ui/lib/utils.ts",
      "content": "import { type ClassValue, clsx } from \"clsx\"\nimport { twMerge } from \"tailwind-merge\"\n\nexport function cn(...inputs: ClassValue[]) {\n  return twMerge(clsx(inputs))\n}\n",
      "type": "registry:lib",
      "target": "@lib/utils.ts"
    }
  ],
  "meta": {
    "tasteblocks": {
      "status": "verified",
      "category": "forms-feedback",
      "tags": [
        "file-upload",
        "drag-drop",
        "progress",
        "cancellable"
      ],
      "renderer": "svg",
      "preview": "previews/kokonut-file-upload.tsx",
      "source": {
        "project": "Kokonut UI",
        "repository": "https://github.com/kokonut-labs/kokonutui",
        "revision": "4aba04e5e1c3e1c7de966554aacbe0cd6a31c77e",
        "retrievedAt": "2026-07-20",
        "files": [
          {
            "shippedPath": "components/kokonut-file-upload/file-upload.tsx",
            "upstreamPath": "components/kokonutui/file-upload.tsx",
            "permalink": "https://github.com/kokonut-labs/kokonutui/blob/4aba04e5e1c3e1c7de966554aacbe0cd6a31c77e/components/kokonutui/file-upload.tsx",
            "upstreamSha256": "sha256:a4e08685bba86205a625fced37fd1a4dcc034d2b8b707c35f36ae27019b34846",
            "contentSha256": "sha256:6d2667e60bab4143355f5357fc57494fbf9e7013d63db214d56850f014a25e35",
            "changes": [
              "Replaced the built-in fake upload timer with a required caller-supplied async upload function, AbortSignal cancellation, and bounded progress reporting.",
              "Replaced regular-expression MIME matching with literal MIME, wildcard MIME, and extension matching; bounded invalid size and progress inputs.",
              "Added a persistent completed state, visible errors, cancellable cleanup, unique SVG mask IDs, live progress, and semantic busy and group states.",
              "Stopped all SMIL, CSS, and Motion movement under reduced motion, increased touch targets, and gated decorative hover movement.",
              "Changed the application utility alias to the bundled relative helper and normalized formatting while preserving the upstream upload illustrations and ring geometry."
            ]
          },
          {
            "shippedPath": "lib/utils.ts",
            "upstreamPath": "lib/utils.ts",
            "permalink": "https://github.com/kokonut-labs/kokonutui/blob/4aba04e5e1c3e1c7de966554aacbe0cd6a31c77e/lib/utils.ts",
            "upstreamSha256": "sha256:9e45d6d21e0d57bf85930ba2bf6fdd9f5f0175d1129844356081a6050975deb1",
            "contentSha256": "sha256:51bbf14cd1f84f49aab2e0dbee420137015d56b6677bb439e83a908cd292cce1",
            "changes": [
              "Normalized formatting and line endings without changing behavior."
            ]
          }
        ]
      },
      "license": {
        "spdx": "MIT",
        "scope": "components/kokonutui/file-upload.tsx and lib/utils.ts",
        "copyright": [
          "Copyright (c) 2025 kokonutUI"
        ],
        "evidence": {
          "upstreamPath": "LICENSE",
          "permalink": "https://github.com/kokonut-labs/kokonutui/blob/4aba04e5e1c3e1c7de966554aacbe0cd6a31c77e/LICENSE",
          "sha256": "sha256:b2e018ad1fd564608cc1ee0c2ad675ce5202c8ed9f5f68e6d09e7b6bc881d5d2",
          "localPath": "registry/sources/kokonut-ui/LICENSE"
        },
        "notices": []
      },
      "assets": [],
      "modifications": [
        {
          "shippedPath": "components/kokonut-file-upload/file-upload.tsx",
          "change": "Preserved the upstream visual treatment while replacing simulated behavior with a real async transport contract, cancellation, strict validation, completed and error states, unique SVG IDs, and complete motion and input accessibility.",
          "reason": "A reusable upload component must never claim success from a timer; it needs caller-owned transport, progress, cancellation, validation, and deterministic cleanup."
        },
        {
          "shippedPath": "lib/utils.ts",
          "change": "Normalized formatting and line endings.",
          "reason": "Match the source batch formatting without changing the copied helper."
        }
      ],
      "dedupe": {
        "family": "asynchronous-file-drop-uploader",
        "sourceHash": "sha256:79219df5495222423276bc11302ea43663905a883e1988299eb4914a2effcac7",
        "contentHash": "sha256:a4c21a15384834b2c2b3bf62a6865f5f1c12a314a84ab57a77130a7cdae2a2bb",
        "structureHash": "sha256:837be6eff2111f60bbffa0040879eedfe95d29d7df14aed26cf4e3f7ef5985cb"
      },
      "verification": {
        "reviewedBy": "Codex",
        "reviewedAt": "2026-07-20"
      }
    }
  },
  "categories": [
    "forms-feedback"
  ],
  "type": "registry:component"
}